README.rst
setup.cfg
setup.py
sndscribe/__init__.py
sndscribe/api.py
sndscribe/config.py
sndscribe/conversions.py
sndscribe/defaultconfig.py
sndscribe/definitions.py
sndscribe/dynamics.py
sndscribe/envir.py
sndscribe/error.py
sndscribe/fraction.py
sndscribe/lilytools.py
sndscribe/measure.py
sndscribe/note.py
sndscribe/optimize.py
sndscribe/pack.py
sndscribe/pulse.py
sndscribe/quantization.py
sndscribe/reduction.py
sndscribe/renderlily.py
sndscribe/score.py
sndscribe/scorefuncs.py
sndscribe/staff.py
sndscribe/test.py
sndscribe/tools.py
sndscribe/track.py
sndscribe/transcribe.py
sndscribe/typehints.py
sndscribe/voice.py
sndscribe.egg-info/PKG-INFO
sndscribe.egg-info/SOURCES.txt
sndscribe.egg-info/dependency_links.txt
sndscribe.egg-info/not-zip-safe
sndscribe.egg-info/requires.txt
sndscribe.egg-info/top_level.txt
sndscribe/data/defaultconfig.yaml
sndscribe/data/microtonal.ily
sndscribe/xml2ly/book_base.py_
sndscribe/xml2ly/book_docbook.py_
sndscribe/xml2ly/book_html.py_
sndscribe/xml2ly/book_latex.py_
sndscribe/xml2ly/book_snippets.py_
sndscribe/xml2ly/book_texinfo.py_
sndscribe/xml2ly/convert-ly.py_
sndscribe/xml2ly/convertrules.py_
sndscribe/xml2ly/fontextract.py_
sndscribe/xml2ly/langdefs.py_
sndscribe/xml2ly/lilylib.py_
sndscribe/xml2ly/lilymidi.py_
sndscribe/xml2ly/musicexp.py_
sndscribe/xml2ly/musicxml.py_
sndscribe/xml2ly/musicxml2ly.py_
sndscribe/xml2ly/rational.py_
sndscribe/xml2ly/safeeval.py_