Metadata-Version: 1.2
Name: sndscribe
Version: 0.3.0
Summary: Translate the spectrum of an audio file into musical notation
Home-page: UNKNOWN
Author: Eduardo Moguillansky
Author-email: eduardo.moguillansky@gmail.com
License: GPL
Platform: UNKNOWN
Classifier: Programming Language :: Python :: 3.6
Classifier: Programming Language :: Python :: 3.7
Requires-Python: >=3.6
